{
  "departamento": 15,
  "municipio": 3,
  "actas": {
    "presidente": {
      "tipo_eleccion": 1,
      "cantidad_papeletas": 21936,
      "votos": {
        "validos_acta": 10620,
        "validos": 10620,
        "nulos": 816,
        "blancos": 1364,
        "invalidos": 0,
        "total_acta": 12800,
        "total_votos": 12800,
        "acta_cuadra": 58,
        "impugnaciones": 0,
        "partidos": {
          "avanza": 105,
          "convergencia": 43,
          "creo": 113,
          "eg": 70,
          "fcn_nacion": 463,
          "libre": 35,
          "mlp": 2503,
          "pan_podemos": 423,
          "phg": 1382,
          "ppt": 67,
          "todos": 218,
          "une": 2554,
          "unidos": 110,
          "unionista": 110,
          "urng_maiz": 290,
          "vamos": 1464,
          "victoria": 179,
          "viva": 178,
          "winaq": 313
        }
      }
    },
    "diputados_parlacen": {
      "tipo_eleccion": 5,
      "cantidad_papeletas": 21961,
      "votos": {
        "validos_acta": 7117,
        "validos": 7117,
        "nulos": 3083,
        "blancos": 2598,
        "invalidos": 2,
        "total_acta": 12800,
        "total_votos": 12798,
        "acta_cuadra": 57,
        "impugnaciones": 0,
        "partidos": {
          "avanza": 213,
          "bien": 472,
          "convergencia": 73,
          "creo": 332,
          "eg": 110,
          "fcn_nacion": 343,
          "fuerza": 48,
          "libre": 29,
          "pan": 197,
          "pc": 85,
          "podemos": 392,
          "semilla": 317,
          "todos": 448,
          "ucn": 94,
          "une": 1228,
          "unidos": 140,
          "unionista": 80,
          "urng_maiz": 472,
          "valor": 106,
          "vamos": 1590,
          "victoria": 115,
          "viva": 122,
          "winaq": 249
        }
      }
    },
    "diputados_nacionales": {
      "tipo_eleccion": 2,
      "cantidad_papeletas": 21937,
      "votos": {
        "validos_acta": 8943,
        "validos": 8945,
        "nulos": 1729,
        "blancos": 2126,
        "invalidos": 0,
        "total_acta": 12800,
        "total_votos": 12800,
        "acta_cuadra": 57,
        "impugnaciones": 0,
        "partidos": {
          "avanza": 93,
          "bien": 532,
          "convergencia": 49,
          "creo": 350,
          "eg": 100,
          "fcn_nacion": 325,
          "fuerza": 31,
          "libre": 34,
          "mlp": 689,
          "pan": 189,
          "pc": 35,
          "phg": 692,
          "podemos": 381,
          "ppt": 47,
          "semilla": 388,
          "todos": 512,
          "ucn": 108,
          "une": 1491,
          "unidos": 124,
          "unionista": 82,
          "urng_maiz": 454,
          "valor": 131,
          "vamos": 1535,
          "victoria": 126,
          "viva": 122,
          "winaq": 244
        }
      }
    },
    "diputados_distritales": {
      "tipo_eleccion": 3,
      "cantidad_papeletas": 21939,
      "votos": {
        "validos_acta": 9980,
        "validos": 9980,
        "nulos": 1180,
        "blancos": 1640,
        "invalidos": 0,
        "total_acta": 12800,
        "total_votos": 12800,
        "acta_cuadra": 58,
        "impugnaciones": 0,
        "partidos": {
          "bien": 499,
          "creo": 918,
          "fcn_nacion": 414,
          "mlp": 713,
          "phg": 713,
          "podemos": 850,
          "semilla": 335,
          "todos": 1027,
          "ucn": 58,
          "une": 1460,
          "unidos": 166,
          "unionista": 47,
          "urng_maiz": 566,
          "valor": 290,
          "vamos": 1628,
          "winaq": 296
        }
      }
    },
    "corporaciones_municipales": {
      "tipo_eleccion": 4,
      "cantidad_papeletas": 21885,
      "votos": {
        "validos_acta": 11400,
        "validos": 11403,
        "nulos": 1203,
        "blancos": 197,
        "invalidos": 0,
        "total_acta": 12800,
        "total_votos": 12803,
        "acta_cuadra": 57,
        "impugnaciones": 2,
        "partidos": {
          "bien": 229,
          "cocerna": 1922,
          "cociear": 1967,
          "cociech": 2601,
          "fcn_nacion": 52,
          "mlp": 267,
          "phg": 364,
          "podemos": 157,
          "semilla": 244,
          "une": 1017,
          "unidos": 145,
          "urng_maiz": 178,
          "vamos": 2260
        }
      }
    }
  }
}