{
  "departamento": 5,
  "municipio": 4,
  "actas": {
    "presidente": {
      "tipo_eleccion": 1,
      "cantidad_papeletas": 6536,
      "votos": {
        "validos_acta": 8994,
        "validos": 8878,
        "nulos": 456,
        "blancos": 798,
        "invalidos": 290,
        "total_acta": 9007,
        "total_votos": 10132,
        "acta_cuadra": 30,
        "impugnaciones": 13,
        "partidos": {
          "avanza": 32,
          "convergencia": 53,
          "creo": 1458,
          "eg": 42,
          "fcn_nacion": 362,
          "libre": 39,
          "mlp": 319,
          "pan_podemos": 662,
          "phg": 1273,
          "ppt": 48,
          "todos": 140,
          "une": 2266,
          "unidos": 33,
          "unionista": 112,
          "urng_maiz": 107,
          "vamos": 1144,
          "victoria": 211,
          "viva": 330,
          "winaq": 247
        }
      }
    },
    "diputados_parlacen": {
      "tipo_eleccion": 5,
      "cantidad_papeletas": 6378,
      "votos": {
        "validos_acta": 7460,
        "validos": 7357,
        "nulos": 1505,
        "blancos": 1216,
        "invalidos": 46,
        "total_acta": 10112,
        "total_votos": 10078,
        "acta_cuadra": 27,
        "impugnaciones": 322,
        "partidos": {
          "avanza": 53,
          "bien": 524,
          "convergencia": 35,
          "creo": 1896,
          "eg": 42,
          "fcn_nacion": 319,
          "fuerza": 577,
          "libre": 24,
          "pan": 208,
          "pc": 99,
          "podemos": 56,
          "semilla": 131,
          "todos": 146,
          "ucn": 1306,
          "une": 990,
          "unidos": 21,
          "unionista": 31,
          "urng_maiz": 59,
          "valor": 95,
          "vamos": 320,
          "victoria": 174,
          "viva": 155,
          "winaq": 96
        }
      }
    },
    "diputados_nacionales": {
      "tipo_eleccion": 2,
      "cantidad_papeletas": 6653,
      "votos": {
        "validos_acta": 8393,
        "validos": 8240,
        "nulos": 898,
        "blancos": 976,
        "invalidos": 326,
        "total_acta": 9259,
        "total_votos": 10114,
        "acta_cuadra": 25,
        "impugnaciones": 343,
        "partidos": {
          "avanza": 31,
          "bien": 650,
          "convergencia": 22,
          "creo": 1807,
          "eg": 48,
          "fcn_nacion": 354,
          "fuerza": 565,
          "libre": 46,
          "mlp": 54,
          "pan": 213,
          "pc": 73,
          "phg": 363,
          "podemos": 56,
          "ppt": 52,
          "semilla": 206,
          "todos": 122,
          "ucn": 1262,
          "une": 1209,
          "unidos": 14,
          "unionista": 57,
          "urng_maiz": 78,
          "valor": 92,
          "vamos": 388,
          "victoria": 190,
          "viva": 168,
          "winaq": 120
        }
      }
    },
    "diputados_distritales": {
      "tipo_eleccion": 3,
      "cantidad_papeletas": 6652,
      "votos": {
        "validos_acta": 8594,
        "validos": 8480,
        "nulos": 792,
        "blancos": 845,
        "invalidos": 14,
        "total_acta": 9844,
        "total_votos": 10117,
        "acta_cuadra": 29,
        "impugnaciones": 8,
        "partidos": {
          "avanza": 28,
          "bien": 654,
          "convergencia": 15,
          "creo": 2065,
          "eg": 47,
          "fcn_nacion": 331,
          "fuerza": 763,
          "libre": 36,
          "mlp": 54,
          "pan": 177,
          "pc": 119,
          "phg": 310,
          "podemos": 47,
          "ppt": 43,
          "semilla": 212,
          "todos": 155,
          "ucn": 1327,
          "une": 1137,
          "unidos": 22,
          "unionista": 46,
          "urng_maiz": 61,
          "valor": 65,
          "vamos": 317,
          "victoria": 203,
          "viva": 143,
          "winaq": 103
        }
      }
    },
    "corporaciones_municipales": {
      "tipo_eleccion": 4,
      "cantidad_papeletas": 6248,
      "votos": {
        "validos_acta": 9616,
        "validos": 9614,
        "nulos": 399,
        "blancos": 127,
        "invalidos": 9,
        "total_acta": 10152,
        "total_votos": 10140,
        "acta_cuadra": 33,
        "impugnaciones": 17,
        "partidos": {
          "creo": 3299,
          "fcn_nacion": 315,
          "fuerza": 809,
          "pc": 154,
          "podemos": 63,
          "ucn": 2279,
          "une": 2430,
          "vamos": 265
        }
      }
    }
  }
}