{
  "mesa": 11690,
  "departamento": 12,
  "municipio": 4,
  "actas": {
    "presidente": {
      "tipo_eleccion": 1,
      "estado_acta": 2,
      "cantidad_papeletas": 248,
      "votos": {
        "validos_acta": 99,
        "validos": 99,
        "nulos": 9,
        "blancos": 23,
        "invalidos": 0,
        "total_acta": 131,
        "total_votos": 131,
        "acta_cuadra": 1,
        "impugnaciones": 0,
        "partidos": {
          "avanza": 5,
          "convergencia": 2,
          "creo": 0,
          "eg": 0,
          "fcn_nacion": 18,
          "libre": 0,
          "mlp": 10,
          "pan_podemos": 1,
          "phg": 1,
          "ppt": 1,
          "todos": 0,
          "une": 48,
          "unidos": 0,
          "unionista": 6,
          "urng_maiz": 0,
          "vamos": 2,
          "victoria": 0,
          "viva": 3,
          "winaq": 2
        }
      }
    },
    "diputados_parlacen": {
      "tipo_eleccion": 5,
      "estado_acta": 2,
      "cantidad_papeletas": 248,
      "votos": {
        "validos_acta": 94,
        "validos": 94,
        "nulos": 13,
        "blancos": 24,
        "invalidos": 0,
        "total_acta": 131,
        "total_votos": 131,
        "acta_cuadra": 1,
        "impugnaciones": 0,
        "partidos": {
          "avanza": 4,
          "bien": 1,
          "convergencia": 0,
          "creo": 0,
          "eg": 0,
          "fcn_nacion": 23,
          "fuerza": 11,
          "libre": 0,
          "pan": 0,
          "pc": 1,
          "podemos": 1,
          "semilla": 1,
          "todos": 0,
          "ucn": 0,
          "une": 31,
          "unidos": 0,
          "unionista": 8,
          "urng_maiz": 0,
          "valor": 0,
          "vamos": 3,
          "victoria": 0,
          "viva": 8,
          "winaq": 2
        }
      }
    },
    "diputados_nacionales": {
      "tipo_eleccion": 2,
      "estado_acta": 2,
      "cantidad_papeletas": 248,
      "votos": {
        "validos_acta": 96,
        "validos": 96,
        "nulos": 8,
        "blancos": 27,
        "invalidos": 0,
        "total_acta": 131,
        "total_votos": 131,
        "acta_cuadra": 1,
        "impugnaciones": 0,
        "partidos": {
          "avanza": 1,
          "bien": 1,
          "convergencia": 0,
          "creo": 0,
          "eg": 1,
          "fcn_nacion": 23,
          "fuerza": 7,
          "libre": 0,
          "mlp": 2,
          "pan": 1,
          "pc": 0,
          "phg": 1,
          "podemos": 1,
          "ppt": 2,
          "semilla": 0,
          "todos": 0,
          "ucn": 1,
          "une": 34,
          "unidos": 0,
          "unionista": 9,
          "urng_maiz": 0,
          "valor": 0,
          "vamos": 3,
          "victoria": 0,
          "viva": 6,
          "winaq": 3
        }
      }
    },
    "diputados_distritales": {
      "tipo_eleccion": 3,
      "estado_acta": 2,
      "cantidad_papeletas": 248,
      "votos": {
        "validos_acta": 98,
        "validos": 98,
        "nulos": 10,
        "blancos": 23,
        "invalidos": 0,
        "total_acta": 131,
        "total_votos": 131,
        "acta_cuadra": 1,
        "impugnaciones": 0,
        "partidos": {
          "bien": 0,
          "convergencia": 0,
          "creo": 0,
          "eg": 0,
          "fcn_nacion": 20,
          "fuerza": 10,
          "libre": 0,
          "mlp": 0,
          "pan": 1,
          "pc": 1,
          "phg": 4,
          "ppt": 0,
          "semilla": 3,
          "todos": 0,
          "ucn": 0,
          "une": 38,
          "unidos": 0,
          "unionista": 10,
          "urng_maiz": 0,
          "valor": 0,
          "vamos": 0,
          "victoria": 0,
          "viva": 5,
          "winaq": 6
        }
      }
    },
    "corporaciones_municipales": {
      "tipo_eleccion": 4,
      "estado_acta": 2,
      "cantidad_papeletas": 248,
      "votos": {
        "validos_acta": 108,
        "validos": 108,
        "nulos": 9,
        "blancos": 14,
        "invalidos": 0,
        "total_acta": 131,
        "total_votos": 131,
        "acta_cuadra": 1,
        "impugnaciones": 0,
        "partidos": {
          "avanza": 4,
          "bien": 1,
          "fcn_nacion": 28,
          "fuerza": 12,
          "phg": 2,
          "semilla": 2,
          "ucn": 0,
          "une": 40,
          "unionista": 8,
          "urng_maiz": 0,
          "vamos": 0,
          "viva": 9,
          "winaq": 2
        }
      }
    }
  }
}