{
  "mesa": 18725,
  "departamento": 18,
  "municipio": 5,
  "actas": {
    "presidente": {
      "tipo_eleccion": 1,
      "estado_acta": 2,
      "cantidad_papeletas": 400,
      "votos": {
        "validos_acta": 209,
        "validos": 209,
        "nulos": 5,
        "blancos": 18,
        "invalidos": 0,
        "total_acta": 232,
        "total_votos": 232,
        "acta_cuadra": 1,
        "impugnaciones": 0,
        "partidos": {
          "avanza": 0,
          "convergencia": 0,
          "creo": 1,
          "eg": 1,
          "fcn_nacion": 3,
          "libre": 1,
          "mlp": 14,
          "pan_podemos": 18,
          "phg": 44,
          "ppt": 0,
          "todos": 4,
          "une": 64,
          "unidos": 3,
          "unionista": 2,
          "urng_maiz": 0,
          "vamos": 20,
          "victoria": 15,
          "viva": 15,
          "winaq": 4
        }
      }
    },
    "diputados_parlacen": {
      "tipo_eleccion": 5,
      "estado_acta": 2,
      "cantidad_papeletas": 400,
      "votos": {
        "validos_acta": 155,
        "validos": 155,
        "nulos": 42,
        "blancos": 27,
        "invalidos": 8,
        "total_acta": 224,
        "total_votos": 224,
        "acta_cuadra": 1,
        "impugnaciones": 0,
        "partidos": {
          "avanza": 0,
          "bien": 29,
          "convergencia": 1,
          "creo": 1,
          "eg": 0,
          "fcn_nacion": 0,
          "fuerza": 6,
          "libre": 0,
          "pan": 2,
          "pc": 2,
          "podemos": 0,
          "semilla": 2,
          "todos": 4,
          "ucn": 7,
          "une": 45,
          "unidos": 1,
          "unionista": 0,
          "urng_maiz": 1,
          "valor": 22,
          "vamos": 8,
          "victoria": 21,
          "viva": 3,
          "winaq": 0
        }
      }
    },
    "diputados_nacionales": {
      "tipo_eleccion": 2,
      "estado_acta": 2,
      "cantidad_papeletas": 400,
      "votos": {
        "validos_acta": 184,
        "validos": 184,
        "nulos": 22,
        "blancos": 24,
        "invalidos": 2,
        "total_acta": 230,
        "total_votos": 230,
        "acta_cuadra": 1,
        "impugnaciones": 0,
        "partidos": {
          "avanza": 0,
          "bien": 34,
          "convergencia": 0,
          "creo": 2,
          "eg": 0,
          "fcn_nacion": 2,
          "fuerza": 4,
          "libre": 0,
          "mlp": 2,
          "pan": 5,
          "pc": 4,
          "phg": 10,
          "podemos": 0,
          "ppt": 1,
          "semilla": 2,
          "todos": 2,
          "ucn": 5,
          "une": 55,
          "unidos": 2,
          "unionista": 2,
          "urng_maiz": 0,
          "valor": 20,
          "vamos": 10,
          "victoria": 17,
          "viva": 5,
          "winaq": 0
        }
      }
    },
    "diputados_distritales": {
      "tipo_eleccion": 3,
      "estado_acta": 2,
      "cantidad_papeletas": 400,
      "votos": {
        "validos_acta": 206,
        "validos": 206,
        "nulos": 11,
        "blancos": 14,
        "invalidos": 1,
        "total_acta": 231,
        "total_votos": 231,
        "acta_cuadra": 1,
        "impugnaciones": 0,
        "partidos": {
          "bien": 34,
          "fcn_nacion": 5,
          "fuerza": 14,
          "libre": 0,
          "mlp": 5,
          "pan": 4,
          "pc": 6,
          "phg": 6,
          "ppt": 0,
          "semilla": 1,
          "todos": 2,
          "ucn": 7,
          "une": 59,
          "unidos": 2,
          "valor": 28,
          "vamos": 9,
          "victoria": 20,
          "viva": 4,
          "winaq": 0
        }
      }
    },
    "corporaciones_municipales": {
      "tipo_eleccion": 4,
      "estado_acta": 2,
      "cantidad_papeletas": 400,
      "votos": {
        "validos_acta": 227,
        "validos": 227,
        "nulos": 0,
        "blancos": 4,
        "invalidos": 1,
        "total_acta": 231,
        "total_votos": 231,
        "acta_cuadra": 1,
        "impugnaciones": 0,
        "partidos": {
          "bien": 36,
          "fcn_nacion": 2,
          "mlp": 2,
          "pc": 2,
          "semilla": 0,
          "ucn": 9,
          "une": 80,
          "valor": 48,
          "vamos": 9,
          "victoria": 39
        }
      }
    }
  }
}