{
  "mesa": 15613,
  "departamento": 14,
  "municipio": 20,
  "actas": {
    "presidente": {
      "tipo_eleccion": 1,
      "estado_acta": 2,
      "cantidad_papeletas": 400,
      "votos": {
        "validos_acta": 153,
        "validos": 153,
        "nulos": 4,
        "blancos": 8,
        "invalidos": 0,
        "total_acta": 165,
        "total_votos": 165,
        "acta_cuadra": 1,
        "impugnaciones": 0,
        "partidos": {
          "avanza": 0,
          "convergencia": 1,
          "creo": 0,
          "eg": 0,
          "fcn_nacion": 2,
          "libre": 0,
          "mlp": 25,
          "pan_podemos": 3,
          "phg": 7,
          "ppt": 0,
          "todos": 5,
          "une": 69,
          "unidos": 2,
          "unionista": 3,
          "urng_maiz": 12,
          "vamos": 13,
          "victoria": 1,
          "viva": 7,
          "winaq": 3
        }
      }
    },
    "diputados_parlacen": {
      "tipo_eleccion": 5,
      "estado_acta": 2,
      "cantidad_papeletas": 400,
      "votos": {
        "validos_acta": 100,
        "validos": 100,
        "nulos": 20,
        "blancos": 45,
        "invalidos": 0,
        "total_acta": 165,
        "total_votos": 165,
        "acta_cuadra": 1,
        "impugnaciones": 0,
        "partidos": {
          "avanza": 1,
          "bien": 0,
          "convergencia": 1,
          "creo": 1,
          "eg": 0,
          "fcn_nacion": 3,
          "fuerza": 0,
          "libre": 0,
          "pan": 3,
          "pc": 7,
          "podemos": 0,
          "semilla": 14,
          "todos": 1,
          "ucn": 6,
          "une": 24,
          "unidos": 0,
          "unionista": 3,
          "urng_maiz": 13,
          "valor": 15,
          "vamos": 5,
          "victoria": 0,
          "viva": 3,
          "winaq": 0
        }
      }
    },
    "diputados_nacionales": {
      "tipo_eleccion": 2,
      "estado_acta": 2,
      "cantidad_papeletas": 400,
      "votos": {
        "validos_acta": 129,
        "validos": 128,
        "nulos": 10,
        "blancos": 26,
        "invalidos": 0,
        "total_acta": 165,
        "total_votos": 164,
        "acta_cuadra": 0,
        "impugnaciones": 0,
        "partidos": {
          "avanza": 1,
          "bien": 1,
          "convergencia": 1,
          "creo": 0,
          "eg": 0,
          "fcn_nacion": 4,
          "fuerza": 0,
          "libre": 0,
          "mlp": 5,
          "pan": 3,
          "pc": 4,
          "phg": 4,
          "podemos": 0,
          "ppt": 1,
          "semilla": 15,
          "todos": 2,
          "ucn": 7,
          "une": 32,
          "unidos": 1,
          "unionista": 2,
          "urng_maiz": 20,
          "valor": 12,
          "vamos": 6,
          "victoria": 1,
          "viva": 6,
          "winaq": 0
        }
      }
    },
    "diputados_distritales": {
      "tipo_eleccion": 3,
      "estado_acta": 2,
      "cantidad_papeletas": 400,
      "votos": {
        "validos_acta": 134,
        "validos": 134,
        "nulos": 10,
        "blancos": 21,
        "invalidos": 0,
        "total_acta": 165,
        "total_votos": 165,
        "acta_cuadra": 1,
        "impugnaciones": 0,
        "partidos": {
          "avanza": 2,
          "bien": 0,
          "convergencia": 2,
          "creo": 0,
          "eg": 0,
          "fcn_nacion": 2,
          "fuerza": 1,
          "libre": 0,
          "mlp": 6,
          "pan": 2,
          "pc": 5,
          "phg": 5,
          "podemos": 1,
          "semilla": 26,
          "todos": 2,
          "ucn": 7,
          "une": 35,
          "unidos": 0,
          "unionista": 2,
          "urng_maiz": 18,
          "valor": 10,
          "vamos": 5,
          "victoria": 1,
          "viva": 2,
          "winaq": 0
        }
      }
    },
    "corporaciones_municipales": {
      "tipo_eleccion": 4,
      "estado_acta": 2,
      "cantidad_papeletas": 400,
      "votos": {
        "validos_acta": 154,
        "validos": 154,
        "nulos": 9,
        "blancos": 2,
        "invalidos": 0,
        "total_acta": 165,
        "total_votos": 165,
        "acta_cuadra": 1,
        "impugnaciones": 0,
        "partidos": {
          "comité_cívico_el_campesino": 14,
          "convergencia": 2,
          "fcn_nacion": 7,
          "pc": 8,
          "phg": 4,
          "semilla": 23,
          "todos": 3,
          "ucn": 9,
          "une": 22,
          "unidos": 0,
          "unionista": 4,
          "urng_maiz": 16,
          "valor": 29,
          "vamos": 8,
          "viva": 5,
          "winaq": 0
        }
      }
    }
  }
}