{
  "mesa": 6510,
  "departamento": 5,
  "municipio": 2,
  "actas": {
    "presidente": {
      "tipo_eleccion": 1,
      "estado_acta": 2,
      "cantidad_papeletas": 0,
      "votos": {
        "validos_acta": 271,
        "validos": 271,
        "nulos": 20,
        "blancos": 5,
        "invalidos": 0,
        "total_acta": 296,
        "total_votos": 296,
        "acta_cuadra": 1,
        "impugnaciones": 1,
        "partidos": {
          "avanza": 1,
          "convergencia": 1,
          "creo": 15,
          "eg": 2,
          "fcn_nacion": 3,
          "libre": 5,
          "mlp": 17,
          "pan_podemos": 14,
          "phg": 59,
          "ppt": 10,
          "todos": 4,
          "une": 63,
          "unidos": 3,
          "unionista": 3,
          "urng_maiz": 7,
          "vamos": 31,
          "victoria": 7,
          "viva": 13,
          "winaq": 13
        }
      }
    },
    "diputados_parlacen": {
      "tipo_eleccion": 5,
      "estado_acta": 2,
      "cantidad_papeletas": 0,
      "votos": {
        "validos_acta": 208,
        "validos": 208,
        "nulos": 67,
        "blancos": 21,
        "invalidos": 0,
        "total_acta": 296,
        "total_votos": 296,
        "acta_cuadra": 1,
        "impugnaciones": 0,
        "partidos": {
          "avanza": 0,
          "bien": 12,
          "convergencia": 2,
          "creo": 26,
          "eg": 3,
          "fcn_nacion": 3,
          "fuerza": 4,
          "libre": 3,
          "pan": 6,
          "pc": 6,
          "podemos": 2,
          "semilla": 28,
          "todos": 12,
          "ucn": 11,
          "une": 38,
          "unidos": 0,
          "unionista": 3,
          "urng_maiz": 4,
          "valor": 14,
          "vamos": 11,
          "victoria": 8,
          "viva": 7,
          "winaq": 5
        }
      }
    },
    "diputados_nacionales": {
      "tipo_eleccion": 2,
      "estado_acta": 2,
      "cantidad_papeletas": 0,
      "votos": {
        "validos_acta": 246,
        "validos": 246,
        "nulos": 27,
        "blancos": 12,
        "invalidos": 0,
        "total_acta": 285,
        "total_votos": 285,
        "acta_cuadra": 1,
        "impugnaciones": 0,
        "partidos": {
          "avanza": 2,
          "bien": 15,
          "convergencia": 2,
          "creo": 17,
          "eg": 1,
          "fcn_nacion": 2,
          "fuerza": 4,
          "libre": 2,
          "mlp": 2,
          "pan": 8,
          "pc": 9,
          "phg": 16,
          "podemos": 1,
          "ppt": 32,
          "semilla": 31,
          "todos": 10,
          "ucn": 7,
          "une": 36,
          "unidos": 1,
          "unionista": 2,
          "urng_maiz": 2,
          "valor": 13,
          "vamos": 12,
          "victoria": 0,
          "viva": 11,
          "winaq": 8
        }
      }
    },
    "diputados_distritales": {
      "tipo_eleccion": 3,
      "estado_acta": 2,
      "cantidad_papeletas": 0,
      "votos": {
        "validos_acta": 268,
        "validos": 268,
        "nulos": 22,
        "blancos": 6,
        "invalidos": 0,
        "total_acta": 296,
        "total_votos": 296,
        "acta_cuadra": 1,
        "impugnaciones": 0,
        "partidos": {
          "avanza": 0,
          "bien": 11,
          "convergencia": 2,
          "creo": 18,
          "eg": 1,
          "fcn_nacion": 6,
          "fuerza": 4,
          "libre": 5,
          "mlp": 0,
          "pan": 4,
          "pc": 12,
          "phg": 28,
          "podemos": 2,
          "ppt": 31,
          "semilla": 37,
          "todos": 8,
          "ucn": 13,
          "une": 41,
          "unidos": 1,
          "unionista": 0,
          "urng_maiz": 0,
          "valor": 12,
          "vamos": 8,
          "victoria": 12,
          "viva": 9,
          "winaq": 3
        }
      }
    },
    "corporaciones_municipales": {
      "tipo_eleccion": 4,
      "estado_acta": 2,
      "cantidad_papeletas": 0,
      "votos": {
        "validos_acta": 282,
        "validos": 282,
        "nulos": 12,
        "blancos": 3,
        "invalidos": 0,
        "total_acta": 297,
        "total_votos": 297,
        "acta_cuadra": 1,
        "impugnaciones": 0,
        "partidos": {
          "convergencia": 3,
          "creo": 31,
          "fcn_nacion": 6,
          "fuerza": 2,
          "libre": 4,
          "pc": 7,
          "phg": 4,
          "podemos": 1,
          "ppt": 82,
          "semilla": 52,
          "todos": 1,
          "ucn": 7,
          "une": 55,
          "valor": 13,
          "vamos": 7,
          "victoria": 4,
          "viva": 3
        }
      }
    }
  }
}