{
  "mesa": 1703,
  "departamento": 0,
  "municipio": 1,
  "actas": {
    "presidente": {
      "tipo_eleccion": 1,
      "estado_acta": 1,
      "cantidad_papeletas": 600,
      "votos": {
        "validos_acta": 211,
        "validos": 211,
        "nulos": 2,
        "blancos": 0,
        "invalidos": 1,
        "total_acta": 213,
        "total_votos": 213,
        "acta_cuadra": 1,
        "impugnaciones": 0,
        "partidos": {
          "avanza": 2,
          "convergencia": 0,
          "creo": 25,
          "eg": 9,
          "fcn_nacion": 7,
          "libre": 3,
          "mlp": 3,
          "pan_podemos": 13,
          "phg": 38,
          "ppt": 1,
          "todos": 4,
          "une": 6,
          "unidos": 0,
          "unionista": 4,
          "urng_maiz": 1,
          "vamos": 50,
          "victoria": 8,
          "viva": 18,
          "winaq": 19
        }
      }
    },
    "diputados_parlacen": {
      "tipo_eleccion": 5,
      "estado_acta": 1,
      "cantidad_papeletas": 600,
      "votos": {
        "validos_acta": 115,
        "validos": 115,
        "nulos": 95,
        "blancos": 1,
        "invalidos": 3,
        "total_acta": 211,
        "total_votos": 211,
        "acta_cuadra": 1,
        "impugnaciones": 0,
        "partidos": {
          "avanza": 1,
          "bien": 2,
          "convergencia": 1,
          "creo": 18,
          "eg": 9,
          "fcn_nacion": 5,
          "fuerza": 4,
          "libre": 1,
          "pan": 10,
          "pc": 2,
          "podemos": 0,
          "semilla": 8,
          "todos": 2,
          "ucn": 2,
          "une": 2,
          "unidos": 1,
          "unionista": 9,
          "urng_maiz": 1,
          "valor": 9,
          "vamos": 8,
          "victoria": 5,
          "viva": 12,
          "winaq": 3
        }
      }
    },
    "diputados_nacionales": {
      "tipo_eleccion": 2,
      "estado_acta": 1,
      "cantidad_papeletas": 600,
      "votos": {
        "validos_acta": 199,
        "validos": 199,
        "nulos": 11,
        "blancos": 0,
        "invalidos": 4,
        "total_acta": 210,
        "total_votos": 210,
        "acta_cuadra": 1,
        "impugnaciones": 0,
        "partidos": {
          "avanza": 2,
          "bien": 6,
          "convergencia": 1,
          "creo": 21,
          "eg": 19,
          "fcn_nacion": 4,
          "fuerza": 4,
          "libre": 1,
          "mlp": 4,
          "pan": 6,
          "pc": 0,
          "phg": 11,
          "podemos": 4,
          "ppt": 1,
          "semilla": 32,
          "todos": 3,
          "ucn": 2,
          "une": 2,
          "unidos": 0,
          "unionista": 12,
          "urng_maiz": 7,
          "valor": 15,
          "vamos": 12,
          "victoria": 4,
          "viva": 18,
          "winaq": 8
        }
      }
    },
    "diputados_distritales": {
      "tipo_eleccion": 3,
      "estado_acta": 1,
      "cantidad_papeletas": 600,
      "votos": {
        "validos_acta": 199,
        "validos": 199,
        "nulos": 12,
        "blancos": 1,
        "invalidos": 2,
        "total_acta": 212,
        "total_votos": 212,
        "acta_cuadra": 1,
        "impugnaciones": 0,
        "partidos": {
          "avanza": 2,
          "bien": 5,
          "convergencia": 1,
          "creo": 25,
          "eg": 13,
          "fcn_nacion": 3,
          "fuerza": 3,
          "libre": 2,
          "mlp": 5,
          "pan": 6,
          "pc": 3,
          "phg": 16,
          "podemos": 3,
          "ppt": 1,
          "semilla": 29,
          "todos": 3,
          "ucn": 3,
          "une": 3,
          "unidos": 1,
          "unionista": 8,
          "urng_maiz": 5,
          "valor": 22,
          "vamos": 13,
          "victoria": 3,
          "viva": 15,
          "winaq": 6
        }
      }
    },
    "corporaciones_municipales": {
      "tipo_eleccion": 4,
      "estado_acta": 1,
      "cantidad_papeletas": 600,
      "votos": {
        "validos_acta": 209,
        "validos": 209,
        "nulos": 5,
        "blancos": 0,
        "invalidos": 0,
        "total_acta": 214,
        "total_votos": 214,
        "acta_cuadra": 1,
        "impugnaciones": 0,
        "partidos": {
          "bien": 1,
          "convergencia": 0,
          "creo": 62,
          "eg": 6,
          "fcn_nacion": 2,
          "fuerza": 5,
          "libre": 3,
          "pc": 1,
          "phg": 6,
          "ppt": 0,
          "semilla": 12,
          "todos": 1,
          "ucn": 3,
          "une": 2,
          "unionista": 89,
          "vamos": 5,
          "victoria": 3,
          "viva": 8
        }
      }
    }
  }
}