{
  "mesa": 6497,
  "departamento": 5,
  "municipio": 2,
  "actas": {
    "presidente": {
      "tipo_eleccion": 1,
      "estado_acta": 2,
      "cantidad_papeletas": 392,
      "votos": {
        "validos_acta": 265,
        "validos": 265,
        "nulos": 13,
        "blancos": 10,
        "invalidos": 0,
        "total_acta": 288,
        "total_votos": 288,
        "acta_cuadra": 1,
        "impugnaciones": 0,
        "partidos": {
          "avanza": 2,
          "convergencia": 2,
          "creo": 10,
          "eg": 1,
          "fcn_nacion": 7,
          "libre": 3,
          "mlp": 15,
          "pan_podemos": 14,
          "phg": 46,
          "ppt": 12,
          "todos": 6,
          "une": 78,
          "unidos": 2,
          "unionista": 2,
          "urng_maiz": 5,
          "vamos": 27,
          "victoria": 9,
          "viva": 11,
          "winaq": 13
        }
      }
    },
    "diputados_parlacen": {
      "tipo_eleccion": 5,
      "estado_acta": 2,
      "cantidad_papeletas": 400,
      "votos": {
        "validos_acta": 191,
        "validos": 191,
        "nulos": 66,
        "blancos": 31,
        "invalidos": 0,
        "total_acta": 288,
        "total_votos": 288,
        "acta_cuadra": 1,
        "impugnaciones": 0,
        "partidos": {
          "avanza": 1,
          "bien": 12,
          "convergencia": 5,
          "creo": 19,
          "eg": 4,
          "fcn_nacion": 12,
          "fuerza": 2,
          "libre": 2,
          "pan": 10,
          "pc": 5,
          "podemos": 0,
          "semilla": 18,
          "todos": 5,
          "ucn": 11,
          "une": 44,
          "unidos": 0,
          "unionista": 2,
          "urng_maiz": 2,
          "valor": 14,
          "vamos": 9,
          "victoria": 7,
          "viva": 4,
          "winaq": 3
        }
      }
    },
    "diputados_nacionales": {
      "tipo_eleccion": 2,
      "estado_acta": 2,
      "cantidad_papeletas": 400,
      "votos": {
        "validos_acta": 235,
        "validos": 235,
        "nulos": 32,
        "blancos": 21,
        "invalidos": 0,
        "total_acta": 288,
        "total_votos": 288,
        "acta_cuadra": 1,
        "impugnaciones": 0,
        "partidos": {
          "avanza": 2,
          "bien": 14,
          "convergencia": 1,
          "creo": 15,
          "eg": 2,
          "fcn_nacion": 10,
          "fuerza": 2,
          "libre": 1,
          "mlp": 5,
          "pan": 8,
          "pc": 1,
          "phg": 12,
          "podemos": 1,
          "ppt": 31,
          "semilla": 29,
          "todos": 3,
          "ucn": 13,
          "une": 49,
          "unidos": 0,
          "unionista": 0,
          "urng_maiz": 4,
          "valor": 11,
          "vamos": 4,
          "victoria": 8,
          "viva": 3,
          "winaq": 6
        }
      }
    },
    "diputados_distritales": {
      "tipo_eleccion": 3,
      "estado_acta": 2,
      "cantidad_papeletas": 400,
      "votos": {
        "validos_acta": 244,
        "validos": 244,
        "nulos": 24,
        "blancos": 20,
        "invalidos": 0,
        "total_acta": 288,
        "total_votos": 288,
        "acta_cuadra": 1,
        "impugnaciones": 0,
        "partidos": {
          "avanza": 2,
          "bien": 8,
          "convergencia": 2,
          "creo": 21,
          "eg": 1,
          "fcn_nacion": 9,
          "fuerza": 5,
          "libre": 2,
          "mlp": 4,
          "pan": 4,
          "pc": 6,
          "phg": 17,
          "podemos": 1,
          "ppt": 26,
          "semilla": 33,
          "todos": 3,
          "ucn": 15,
          "une": 53,
          "unidos": 0,
          "unionista": 0,
          "urng_maiz": 5,
          "valor": 7,
          "vamos": 5,
          "victoria": 6,
          "viva": 2,
          "winaq": 7
        }
      }
    },
    "corporaciones_municipales": {
      "tipo_eleccion": 4,
      "estado_acta": 2,
      "cantidad_papeletas": 400,
      "votos": {
        "validos_acta": 269,
        "validos": 269,
        "nulos": 13,
        "blancos": 6,
        "invalidos": 0,
        "total_acta": 288,
        "total_votos": 288,
        "acta_cuadra": 1,
        "impugnaciones": 0,
        "partidos": {
          "convergencia": 3,
          "creo": 24,
          "fcn_nacion": 9,
          "fuerza": 0,
          "libre": 2,
          "pc": 3,
          "phg": 5,
          "podemos": 1,
          "ppt": 72,
          "semilla": 52,
          "todos": 1,
          "ucn": 20,
          "une": 60,
          "valor": 15,
          "vamos": 1,
          "victoria": 1,
          "viva": 0
        }
      }
    }
  }
}