{"mesa":5469,"departamento":3,"municipio":5,"actas":{"presidente_y_vicepresidente":{"tipo_eleccion":1,"estado_acta":2,"cantidad_papeletas":400,"votos":{"validos_acta":277,"validos":277,"nulos":6,"blancos":71,"invalidos":0,"total_acta":354,"total_votos":354,"acta_cuadra":1,"impugnaciones":0,"desglose":[{"VAMOS":47},{"TODOS":5},{"UNE":80},{"UNIONISTA":2},{"CONVERGENCIA":2},{"CREO":2},{"FCN_NACION":11},{"WINAQ":8},{"PPT":2},{"UNIDOS":0},{"EG":0},{"URNG_MAIZ":2},{"VICTORIA":5},{"PHG":17},{"VIVA":5},{"AVANZA":4},{"LIBRE":12},{"PAN_PODEMOS":34},{"MLP":39}]}},"diputados_listado_nacional":{"tipo_eleccion":2,"estado_acta":2,"cantidad_papeletas":400,"votos":{"validos_acta":260,"validos":260,"nulos":21,"blancos":73,"invalidos":0,"total_acta":354,"total_votos":354,"acta_cuadra":1,"impugnaciones":0,"desglose":[{"PHG":8},{"VAMOS":18},{"TODOS":1},{"UNE":72},{"VALOR":2},{"UNIONISTA":3},{"FUERZA":5},{"FCN_NACION":12},{"WINAQ":2},{"UCN":10},{"EG":3},{"URNG_MAIZ":2},{"PAN":13},{"PPT":2},{"PC":35},{"VICTORIA":1},{"SEMILLA":8},{"VIVA":7},{"CREO":6},{"CONVERGENCIA":5},{"UNIDOS":0},{"PODEMOS":21},{"BIEN":2},{"LIBRE":16},{"AVANZA":0},{"MLP":6}]}},"parlamento_centroamericano":{"tipo_eleccion":5,"estado_acta":2,"cantidad_papeletas":400,"votos":{"validos_acta":219,"validos":219,"nulos":36,"blancos":99,"invalidos":0,"total_acta":354,"total_votos":354,"acta_cuadra":1,"impugnaciones":0,"desglose":[{"LIBRE":13},{"UNIONISTA":2},{"VAMOS":15},{"FUERZA":4},{"TODOS":1},{"VALOR":2},{"FCN_NACION":13},{"UCN":14},{"EG":1},{"WINAQ":1},{"SEMILLA":7},{"CREO":10},{"UNE":50},{"PAN":12},{"UNIDOS":0},{"URNG_MAIZ":2},{"VICTORIA":2},{"VIVA":3},{"PODEMOS":17},{"BIEN":5},{"CONVERGENCIA":4},{"PC":39},{"AVANZA":2}]}},"corporacion_municipal":{"tipo_eleccion":4,"estado_acta":2,"cantidad_papeletas":400,"votos":{"validos_acta":335,"validos":335,"nulos":9,"blancos":10,"invalidos":0,"total_acta":354,"total_votos":354,"acta_cuadra":1,"impugnaciones":0,"desglose":[{"PC":125},{"FCN_NACION":5},{"PODEMOS":31},{"VAMOS":20},{"UNE":125},{"UCN":10},{"LIBRE":19}]}},"diputados_distritales":{"tipo_eleccion":3,"estado_acta":2,"cantidad_papeletas":400,"votos":{"validos_acta":275,"validos":275,"nulos":16,"blancos":63,"invalidos":0,"total_acta":354,"total_votos":354,"acta_cuadra":1,"impugnaciones":0,"desglose":[{"TODOS":1},{"VAMOS":20},{"EG":4},{"FCN_NACION":17},{"CREO":10},{"CONVERGENCIA":6},{"VIVA":6},{"PAN":10},{"BIEN":2},{"URNG_MAIZ":1},{"PPT":2},{"WINAQ":1},{"VICTORIA":5},{"PODEMOS":18},{"UNIDOS":0},{"PHG":1},{"UNE":71},{"PC":41},{"UCN":11},{"FUERZA":2},{"UNIONISTA":0},{"VALOR":3},{"SEMILLA":13},{"AVANZA":0},{"MLP":10},{"LIBRE":20}]}}}}