{"mesa":17818,"departamento":17,"municipio":7,"actas":{"presidente_y_vicepresidente":{"tipo_eleccion":1,"estado_acta":2,"cantidad_papeletas":380,"votos":{"validos_acta":181,"validos":181,"nulos":8,"blancos":22,"invalidos":0,"total_acta":211,"total_votos":211,"acta_cuadra":1,"impugnaciones":0,"desglose":[{"VAMOS":15},{"TODOS":4},{"UNE":66},{"UNIONISTA":0},{"CONVERGENCIA":1},{"CREO":3},{"FCN_NACION":3},{"WINAQ":4},{"PPT":0},{"UNIDOS":0},{"EG":0},{"URNG_MAIZ":2},{"VICTORIA":0},{"PHG":19},{"VIVA":18},{"AVANZA":0},{"LIBRE":0},{"PAN_PODEMOS":14},{"MLP":32}]}},"diputados_listado_nacional":{"tipo_eleccion":2,"estado_acta":2,"cantidad_papeletas":404,"votos":{"validos_acta":171,"validos":171,"nulos":22,"blancos":18,"invalidos":0,"total_acta":211,"total_votos":211,"acta_cuadra":1,"impugnaciones":0,"desglose":[{"PHG":3},{"VAMOS":5},{"TODOS":1},{"UNE":61},{"VALOR":3},{"UNIONISTA":0},{"FUERZA":1},{"FCN_NACION":0},{"WINAQ":3},{"UCN":0},{"EG":0},{"URNG_MAIZ":1},{"PAN":3},{"PPT":0},{"PC":0},{"VICTORIA":0},{"SEMILLA":1},{"VIVA":3},{"CREO":11},{"CONVERGENCIA":0},{"UNIDOS":0},{"PODEMOS":1},{"BIEN":3},{"LIBRE":0},{"AVANZA":0},{"MLP":0}]}},"parlamento_centroamericano":{"tipo_eleccion":5,"estado_acta":2,"cantidad_papeletas":400,"votos":{"validos_acta":146,"validos":146,"nulos":38,"blancos":27,"invalidos":0,"total_acta":211,"total_votos":211,"acta_cuadra":1,"impugnaciones":0,"desglose":[{"LIBRE":2},{"UNIONISTA":0},{"VAMOS":6},{"FUERZA":1},{"TODOS":0},{"VALOR":0},{"FCN_NACION":2},{"UCN":1},{"EG":0},{"WINAQ":0},{"SEMILLA":1},{"CREO":13},{"UNE":57},{"PAN":3},{"UNIDOS":0},{"URNG_MAIZ":1},{"VICTORIA":1},{"VIVA":4},{"PODEMOS":1},{"BIEN":52},{"CONVERGENCIA":0},{"PC":0},{"AVANZA":1}]}},"corporacion_municipal":{"tipo_eleccion":4,"estado_acta":2,"cantidad_papeletas":400,"votos":{"validos_acta":206,"validos":206,"nulos":3,"blancos":2,"invalidos":0,"total_acta":211,"total_votos":211,"acta_cuadra":1,"impugnaciones":0,"desglose":[{"UNE":86},{"BIEN":109},{"SEMILLA":1},{"MLP":10},{"PODEMOS":0}]}},"diputados_distritales":{"tipo_eleccion":3,"estado_acta":2,"cantidad_papeletas":400,"votos":{"validos_acta":183,"validos":183,"nulos":11,"blancos":17,"invalidos":0,"total_acta":211,"total_votos":211,"acta_cuadra":1,"impugnaciones":0,"desglose":[{"UNE":65},{"UCN":2},{"BIEN":63},{"CREO":11},{"UNIONISTA":1},{"FUERZA":1},{"VALOR":1},{"WINAQ":1},{"FCN_NACION":2},{"VAMOS":8},{"EG":0},{"UNIDOS":1},{"SEMILLA":3},{"TODOS":2},{"CONVERGENCIA":0},{"PHG":1},{"PAN":0},{"PODEMOS":3},{"URNG_MAIZ":0},{"AVANZA":2},{"VIVA":6},{"MLP":10},{"PC":0}]}}}}