{"mesa":7816,"departamento":6,"municipio":13,"actas":{"presidente_y_vicepresidente":{"tipo_eleccion":1,"estado_acta":2,"cantidad_papeletas":380,"votos":{"validos_acta":220,"validos":220,"nulos":11,"blancos":47,"invalidos":1,"total_acta":278,"total_votos":278,"acta_cuadra":1,"impugnaciones":0,"desglose":[{"VAMOS":19},{"TODOS":2},{"UNE":129},{"UNIONISTA":5},{"CONVERGENCIA":2},{"CREO":7},{"FCN_NACION":3},{"WINAQ":4},{"PPT":4},{"UNIDOS":4},{"EG":0},{"URNG_MAIZ":3},{"VICTORIA":5},{"PHG":9},{"VIVA":6},{"AVANZA":3},{"LIBRE":0},{"PAN_PODEMOS":9},{"MLP":6}]}},"diputados_listado_nacional":{"tipo_eleccion":2,"estado_acta":2,"cantidad_papeletas":380,"votos":{"validos_acta":211,"validos":211,"nulos":10,"blancos":55,"invalidos":3,"total_acta":276,"total_votos":276,"acta_cuadra":1,"impugnaciones":0,"desglose":[{"PHG":4},{"VAMOS":9},{"TODOS":1},{"UNE":79},{"VALOR":0},{"UNIONISTA":6},{"FUERZA":2},{"FCN_NACION":0},{"WINAQ":0},{"UCN":77},{"EG":2},{"URNG_MAIZ":1},{"PAN":5},{"PPT":1},{"PC":2},{"VICTORIA":3},{"SEMILLA":2},{"VIVA":3},{"CREO":3},{"CONVERGENCIA":2},{"UNIDOS":1},{"PODEMOS":1},{"BIEN":6},{"LIBRE":0},{"AVANZA":1},{"MLP":0}]}},"parlamento_centroamericano":{"tipo_eleccion":5,"estado_acta":2,"cantidad_papeletas":380,"votos":{"validos_acta":192,"validos":192,"nulos":14,"blancos":70,"invalidos":3,"total_acta":276,"total_votos":276,"acta_cuadra":1,"impugnaciones":0,"desglose":[{"LIBRE":2},{"UNIONISTA":5},{"VAMOS":7},{"FUERZA":4},{"TODOS":4},{"VALOR":0},{"FCN_NACION":1},{"UCN":67},{"EG":2},{"WINAQ":0},{"SEMILLA":3},{"CREO":3},{"UNE":66},{"PAN":3},{"UNIDOS":5},{"URNG_MAIZ":0},{"VICTORIA":6},{"VIVA":2},{"PODEMOS":1},{"BIEN":5},{"CONVERGENCIA":0},{"PC":5},{"AVANZA":1}]}},"corporacion_municipal":{"tipo_eleccion":4,"estado_acta":2,"cantidad_papeletas":380,"votos":{"validos_acta":252,"validos":252,"nulos":19,"blancos":7,"invalidos":1,"total_acta":278,"total_votos":278,"acta_cuadra":1,"impugnaciones":0,"desglose":[{"UNE":110},{"UNIONISTA":9},{"CREO":9},{"PHG":1},{"FUERZA":9},{"AVANZA":0},{"UCN":109},{"MLP":2},{"FCN_NACION":3}]}},"diputados_distritales":{"tipo_eleccion":3,"estado_acta":2,"cantidad_papeletas":380,"votos":{"validos_acta":220,"validos":220,"nulos":15,"blancos":43,"invalidos":1,"total_acta":278,"total_votos":278,"acta_cuadra":1,"impugnaciones":0,"desglose":[{"VAMOS":8},{"AVANZA":4},{"UNE":84},{"VIVA":2},{"VALOR":0},{"WINAQ":2},{"TODOS":4},{"CREO":3},{"UCN":82},{"PAN":3},{"FCN_NACION":2},{"UNIDOS":1},{"VICTORIA":0},{"BIEN":3},{"SEMILLA":2},{"PHG":2},{"UNIONISTA":7},{"PC":2},{"MLP":1},{"EG":2},{"FUERZA":6}]}}}}