{"mesa":11037,"departamento":11,"municipio":1,"actas":{"presidente_y_vicepresidente":{"tipo_eleccion":1,"estado_acta":2,"cantidad_papeletas":380,"votos":{"validos_acta":189,"validos":189,"nulos":11,"blancos":24,"invalidos":0,"total_acta":224,"total_votos":224,"acta_cuadra":1,"impugnaciones":0,"desglose":[{"VAMOS":18},{"TODOS":2},{"UNE":107},{"UNIONISTA":2},{"CONVERGENCIA":0},{"CREO":0},{"FCN_NACION":2},{"WINAQ":2},{"PPT":1},{"UNIDOS":1},{"EG":1},{"URNG_MAIZ":2},{"VICTORIA":1},{"PHG":6},{"VIVA":2},{"AVANZA":0},{"LIBRE":0},{"PAN_PODEMOS":4},{"MLP":38}]}},"diputados_listado_nacional":{"tipo_eleccion":2,"estado_acta":2,"cantidad_papeletas":380,"votos":{"validos_acta":172,"validos":172,"nulos":25,"blancos":27,"invalidos":0,"total_acta":224,"total_votos":224,"acta_cuadra":1,"impugnaciones":0,"desglose":[{"PHG":2},{"VAMOS":9},{"TODOS":6},{"UNE":69},{"VALOR":30},{"UNIONISTA":1},{"FUERZA":3},{"FCN_NACION":1},{"WINAQ":0},{"UCN":5},{"EG":0},{"URNG_MAIZ":3},{"PAN":1},{"PPT":0},{"PC":0},{"VICTORIA":1},{"SEMILLA":3},{"VIVA":1},{"CREO":2},{"CONVERGENCIA":0},{"UNIDOS":1},{"PODEMOS":0},{"BIEN":12},{"LIBRE":0},{"AVANZA":2},{"MLP":20}]}},"parlamento_centroamericano":{"tipo_eleccion":5,"estado_acta":2,"cantidad_papeletas":380,"votos":{"validos_acta":162,"validos":162,"nulos":27,"blancos":35,"invalidos":0,"total_acta":224,"total_votos":224,"acta_cuadra":1,"impugnaciones":0,"desglose":[{"LIBRE":0},{"UNIONISTA":1},{"VAMOS":12},{"FUERZA":4},{"TODOS":3},{"VALOR":38},{"FCN_NACION":1},{"UCN":3},{"EG":0},{"WINAQ":0},{"SEMILLA":5},{"CREO":3},{"UNE":57},{"PAN":0},{"UNIDOS":1},{"URNG_MAIZ":5},{"VICTORIA":1},{"VIVA":2},{"PODEMOS":0},{"BIEN":24},{"CONVERGENCIA":1},{"PC":1},{"AVANZA":0}]}},"corporacion_municipal":{"tipo_eleccion":4,"estado_acta":2,"cantidad_papeletas":380,"votos":{"validos_acta":183,"validos":183,"nulos":29,"blancos":12,"invalidos":0,"total_acta":224,"total_votos":224,"acta_cuadra":1,"impugnaciones":0,"desglose":[{"TODOS":3},{"VALOR":41},{"VAMOS":20},{"UNE":50},{"BIEN":31},{"FCN_NACION":1},{"MLP":20},{"SEMILLA":5},{"EG":0},{"PODEMOS":0},{"CREO":3},{"UNIDOS":1},{"PC":0},{"UCN":3},{"FUERZA":5}]}},"diputados_distritales":{"tipo_eleccion":3,"estado_acta":2,"cantidad_papeletas":370,"votos":{"validos_acta":176,"validos":176,"nulos":26,"blancos":22,"invalidos":0,"total_acta":224,"total_votos":224,"acta_cuadra":1,"impugnaciones":0,"desglose":[{"VAMOS":8},{"TODOS":9},{"EG":0},{"WINAQ":0},{"URNG_MAIZ":5},{"FUERZA":3},{"FCN_NACION":1},{"MLP":23},{"PHG":1},{"VALOR":40},{"PODEMOS":0},{"UNE":57},{"UNIDOS":1},{"CREO":0},{"VIVA":1},{"SEMILLA":4},{"UNIONISTA":1},{"VICTORIA":1},{"LIBRE":0},{"PPT":0},{"BIEN":19},{"PC":0},{"UCN":2}]}}}}