{"mesa":8172,"departamento":7,"municipio":6,"actas":{"presidente_y_vicepresidente":{"tipo_eleccion":1,"estado_acta":2,"cantidad_papeletas":380,"votos":{"validos_acta":268,"validos":268,"nulos":8,"blancos":23,"invalidos":0,"total_acta":299,"total_votos":299,"acta_cuadra":1,"impugnaciones":0,"desglose":[{"VAMOS":33},{"TODOS":3},{"UNE":158},{"UNIONISTA":0},{"CONVERGENCIA":0},{"CREO":3},{"FCN_NACION":32},{"WINAQ":2},{"PPT":1},{"UNIDOS":1},{"EG":1},{"URNG_MAIZ":3},{"VICTORIA":2},{"PHG":3},{"VIVA":1},{"AVANZA":0},{"LIBRE":0},{"PAN_PODEMOS":4},{"MLP":21}]}},"diputados_listado_nacional":{"tipo_eleccion":2,"estado_acta":2,"cantidad_papeletas":380,"votos":{"validos_acta":264,"validos":264,"nulos":10,"blancos":25,"invalidos":0,"total_acta":299,"total_votos":299,"acta_cuadra":1,"impugnaciones":0,"desglose":[{"PHG":1},{"VAMOS":43},{"TODOS":1},{"UNE":153},{"VALOR":0},{"UNIONISTA":1},{"FUERZA":4},{"FCN_NACION":49},{"WINAQ":2},{"UCN":1},{"EG":0},{"URNG_MAIZ":1},{"PAN":0},{"PPT":0},{"PC":1},{"VICTORIA":1},{"SEMILLA":0},{"VIVA":1},{"CREO":0},{"CONVERGENCIA":0},{"UNIDOS":0},{"PODEMOS":2},{"BIEN":3},{"LIBRE":0},{"AVANZA":0},{"MLP":0}]}},"parlamento_centroamericano":{"tipo_eleccion":5,"estado_acta":2,"cantidad_papeletas":380,"votos":{"validos_acta":245,"validos":245,"nulos":15,"blancos":39,"invalidos":0,"total_acta":299,"total_votos":299,"acta_cuadra":1,"impugnaciones":0,"desglose":[{"LIBRE":0},{"UNIONISTA":0},{"VAMOS":41},{"FUERZA":2},{"TODOS":0},{"VALOR":0},{"FCN_NACION":45},{"UCN":0},{"EG":1},{"WINAQ":0},{"SEMILLA":1},{"CREO":2},{"UNE":140},{"PAN":0},{"UNIDOS":1},{"URNG_MAIZ":0},{"VICTORIA":2},{"VIVA":5},{"PODEMOS":0},{"BIEN":3},{"CONVERGENCIA":1},{"PC":1},{"AVANZA":0}]}},"corporacion_municipal":{"tipo_eleccion":4,"estado_acta":2,"cantidad_papeletas":380,"votos":{"validos_acta":283,"validos":283,"nulos":8,"blancos":8,"invalidos":0,"total_acta":299,"total_votos":299,"acta_cuadra":1,"impugnaciones":0,"desglose":[{"VAMOS":48},{"UNE":170},{"FCN_NACION":56},{"FUERZA":5},{"WINAQ":0},{"PODEMOS":1},{"PHG":3},{"MLP":0}]}},"diputados_distritales":{"tipo_eleccion":3,"estado_acta":2,"cantidad_papeletas":380,"votos":{"validos_acta":265,"validos":265,"nulos":12,"blancos":22,"invalidos":0,"total_acta":299,"total_votos":299,"acta_cuadra":1,"impugnaciones":0,"desglose":[{"TODOS":0},{"VAMOS":40},{"BIEN":2},{"PC":0},{"FCN_NACION":48},{"WINAQ":0},{"URNG_MAIZ":2},{"EG":1},{"VICTORIA":3},{"UCN":3},{"SEMILLA":1},{"FUERZA":5},{"PODEMOS":0},{"PHG":1},{"UNIDOS":0},{"UNE":158},{"MLP":1}]}}}}