{"mesa":5936,"departamento":3,"municipio":16,"actas":{"presidente_y_vicepresidente":{"tipo_eleccion":1,"estado_acta":2,"cantidad_papeletas":400,"votos":{"validos_acta":211,"validos":211,"nulos":14,"blancos":20,"invalidos":0,"total_acta":245,"total_votos":245,"acta_cuadra":1,"impugnaciones":0,"desglose":[{"VAMOS":41},{"TODOS":7},{"UNE":31},{"UNIONISTA":3},{"CONVERGENCIA":0},{"CREO":2},{"FCN_NACION":13},{"WINAQ":4},{"PPT":1},{"UNIDOS":1},{"EG":3},{"URNG_MAIZ":7},{"VICTORIA":10},{"PHG":31},{"VIVA":12},{"AVANZA":0},{"LIBRE":4},{"PAN_PODEMOS":25},{"MLP":16}]}},"diputados_listado_nacional":{"tipo_eleccion":2,"estado_acta":2,"cantidad_papeletas":401,"votos":{"validos_acta":185,"validos":185,"nulos":23,"blancos":37,"invalidos":0,"total_acta":245,"total_votos":245,"acta_cuadra":1,"impugnaciones":0,"desglose":[{"PHG":6},{"VAMOS":17},{"TODOS":9},{"UNE":15},{"VALOR":9},{"UNIONISTA":3},{"FUERZA":2},{"FCN_NACION":29},{"WINAQ":3},{"UCN":9},{"EG":8},{"URNG_MAIZ":5},{"PAN":15},{"PPT":1},{"PC":7},{"VICTORIA":2},{"SEMILLA":7},{"VIVA":13},{"CREO":4},{"CONVERGENCIA":0},{"UNIDOS":0},{"PODEMOS":6},{"BIEN":2},{"LIBRE":10},{"AVANZA":0},{"MLP":3}]}},"parlamento_centroamericano":{"tipo_eleccion":5,"estado_acta":2,"cantidad_papeletas":400,"votos":{"validos_acta":158,"validos":158,"nulos":52,"blancos":35,"invalidos":0,"total_acta":245,"total_votos":245,"acta_cuadra":1,"impugnaciones":0,"desglose":[{"LIBRE":8},{"UNIONISTA":1},{"VAMOS":14},{"FUERZA":1},{"TODOS":6},{"VALOR":3},{"FCN_NACION":37},{"UCN":8},{"EG":7},{"WINAQ":2},{"SEMILLA":2},{"CREO":6},{"UNE":16},{"PAN":8},{"UNIDOS":1},{"URNG_MAIZ":3},{"VICTORIA":2},{"VIVA":10},{"PODEMOS":4},{"BIEN":3},{"CONVERGENCIA":0},{"PC":13},{"AVANZA":3}]}},"corporacion_municipal":{"tipo_eleccion":4,"estado_acta":2,"cantidad_papeletas":400,"votos":{"validos_acta":227,"validos":227,"nulos":15,"blancos":3,"invalidos":0,"total_acta":245,"total_votos":245,"acta_cuadra":1,"impugnaciones":0,"desglose":[{"EG":12},{"FCN_NACION":79},{"VIVA":14},{"PHG":2},{"UNE":15},{"PODEMOS":20},{"VALOR":11},{"VAMOS":7},{"UCN":13},{"PC":14},{"LIBRE":31},{"TODOS":9}]}},"diputados_distritales":{"tipo_eleccion":3,"estado_acta":2,"cantidad_papeletas":389,"votos":{"validos_acta":188,"validos":188,"nulos":22,"blancos":35,"invalidos":0,"total_acta":245,"total_votos":245,"acta_cuadra":1,"impugnaciones":0,"desglose":[{"TODOS":7},{"VAMOS":21},{"EG":6},{"FCN_NACION":28},{"CREO":4},{"CONVERGENCIA":2},{"VIVA":12},{"PAN":8},{"BIEN":4},{"URNG_MAIZ":3},{"PPT":4},{"WINAQ":3},{"VICTORIA":3},{"PODEMOS":5},{"UNIDOS":0},{"PHG":7},{"UNE":20},{"PC":10},{"UCN":9},{"FUERZA":2},{"UNIONISTA":3},{"VALOR":9},{"SEMILLA":4},{"AVANZA":0},{"MLP":5},{"LIBRE":9}]}}}}